setup.cfg
setup.py
abl/__init__.py
abl.util.egg-info/PKG-INFO
abl.util.egg-info/SOURCES.txt
abl.util.egg-info/dependency_links.txt
abl.util.egg-info/not-zip-safe
abl.util.egg-info/requires.txt
abl.util.egg-info/top_level.txt
abl/util/__init__.py
abl/util/dispatch.py
abl/util/lockfile.py
abl/util/memoization.py
abl/util/misc.py
abl/util/stream.py
abl/util/test_decorators.py
test/test_bunch.py
test/test_dispatch.py
test/test_lockfile.py
test/test_memoization.py
test/test_misc.py
test/test_streams.py