Metadata-Version: 1.0
Name: abl.util
Version: 0.1.12
Summary: A package that contains various helpful classes and functions used widely in the Ableton Python code base.
Home-page: UNKNOWN
Author: Diez B. Roggisch
Author-email: diez.roggisch@ableton.com
License: MIT
Platform: UNKNOWN
Classifier: Development Status :: 5 - Production/Stable
Classifier: License :: OSI Approved :: MIT License
Classifier: Operating System :: OS Independent
Classifier: Programming Language :: Python
Classifier: Intended Audience :: Developers
Classifier: Topic :: Utilities
